jupyter_releaser/__init__.py
jupyter_releaser/__main__.py
jupyter_releaser/changelog.py
jupyter_releaser/cli.py
jupyter_releaser/lib.py
jupyter_releaser/mock_github.py
jupyter_releaser/npm.py
jupyter_releaser/py.typed
jupyter_releaser/python.py
jupyter_releaser/schema.json
jupyter_releaser/tee.py
jupyter_releaser/util.py
jupyter_releaser/actions/__init__.py
jupyter_releaser/actions/common.py
jupyter_releaser/actions/finalize_release.py
jupyter_releaser/actions/generate_changelog.py
jupyter_releaser/actions/populate_release.py
jupyter_releaser/actions/prep_release.py
jupyter_releaser/actions/publish_changelog.py
jupyter_releaser-1.10.2.dist-info/METADATA
jupyter_releaser-1.10.2.dist-info/WHEEL
jupyter_releaser-1.10.2.dist-info/entry_points.txt
jupyter_releaser-1.10.2.dist-info/licenses/LICENSE
jupyter_releaser-1.10.2.dist-info/RECORD
