Metadata-Version: 2.4
Name: jupyter_releaser
Version: 1.10.2
Summary: Jupyter Releaser for Python and/or npm packages.
Project-URL: Homepage, https://jupyter.org
Author-email: Jupyter Development Team <jupyter@googlegroups.com>
License: Copyright (c) 2021 Project Jupyter Contributors
License-File: LICENSE
Keywords: ipython,jupyter
Classifier: Intended Audience :: Developers
Classifier: Intended Audience :: Science/Research
Classifier: Intended Audience :: System Administrators
Classifier: License :: OSI Approved :: BSD License
Classifier: Programming Language :: Python
Classifier: Programming Language :: Python :: 3.10
Classifier: Programming Language :: Python :: 3.11
Classifier: Programming Language :: Python :: 3.12
Classifier: Programming Language :: Python :: 3.13
Requires-Python: >=3.10
Requires-Dist: click<8.2.0
Requires-Dist: ghapi<=1.0.4
Requires-Dist: github-activity<2,>=1.1.1
Requires-Dist: importlib-resources
Requires-Dist: jsonschema>=3.0.1
Requires-Dist: mdformat
Requires-Dist: packaging
Requires-Dist: pipx
Requires-Dist: pkginfo
Requires-Dist: pypiserver==2.2.0; python_version < '3.13'
Requires-Dist: pypiserver==2.3.2; python_version >= '3.13'
Requires-Dist: requests
Requires-Dist: requests-cache
Requires-Dist: toml~=0.10
Provides-Extra: docs
Requires-Dist: myst-parser; extra == 'docs'
Requires-Dist: numpydoc; extra == 'docs'
Requires-Dist: pip; extra == 'docs'
Requires-Dist: pydata-sphinx-theme; extra == 'docs'
Requires-Dist: sphinx; extra == 'docs'
Requires-Dist: sphinx-autobuild; extra == 'docs'
Requires-Dist: sphinx-click; extra == 'docs'
Requires-Dist: sphinx-copybutton; extra == 'docs'
Requires-Dist: sphinxcontrib-spelling; extra == 'docs'
Provides-Extra: test
Requires-Dist: fastapi; extra == 'test'
Requires-Dist: pre-commit; extra == 'test'
Requires-Dist: pytest-mock; extra == 'test'
Requires-Dist: pytest-xdist[psutil]; extra == 'test'
Requires-Dist: pytest>=7.0; extra == 'test'
Requires-Dist: ruamel-yaml<0.19; extra == 'test'
Requires-Dist: uvicorn; extra == 'test'
